README.md
setup.py
rawdata_loader/__init__.py
rawdata_loader/load_functions.py
rawdata_loader.egg-info/PKG-INFO
rawdata_loader.egg-info/SOURCES.txt
rawdata_loader.egg-info/dependency_links.txt
rawdata_loader.egg-info/top_level.txt