Metadata-Version: 1.1
Name: rawdata-loader
Version: 0.3
Summary: Tools for Guardian raw data handling
Home-page: UNKNOWN
Author: Noam Nisenholz
Author-email: noamholz@guardian-optech.com
License: UNKNOWN
Platform: UNKNOWN
Classifier: Programming Language :: Python :: 3.6
